Metadata-Version: 2.1
Name: rinoh-typeface-impact
Version: 0.1.0
Summary: Impact typeface
Home-page: https://github.com/brechtm/rinoh-typeface-impact
Author: Brecht Machiels
Author-email: brecht@mos6581.org
License: Microsoft Core fonts for the Web – End-user license agreement
Keywords: opentype font
Platform: UNKNOWN
Classifier: Intended Audience :: Developers
Classifier: Intended Audience :: End Users/Desktop
Classifier: Operating System :: OS Independent
Classifier: Programming Language :: Python
Classifier: Programming Language :: Python :: 3
Classifier: Topic :: Text Processing :: Fonts
